LICENSE
MANIFEST.in
README
publish.bash
setup.bash
setup.py
src/commons/__init__.py
src/commons/all.py
src/commons/async.py
src/commons/clients.py
src/commons/control.py
src/commons/decs.py
src/commons/environ.py
src/commons/exceps.py
src/commons/files.py
src/commons/interp.py
src/commons/log.py
src/commons/misc.py
src/commons/networking.py
src/commons/path.py
src/commons/progress.py
src/commons/seqs.py
src/commons/servers.py
src/commons/setup.py
src/commons/sqlhash.py
src/commons/startup.py
src/commons/strs.py
src/commons/structs.py
src/commons/threads.py
src/commons/trace.py
src/commons.egg-info/PKG-INFO
src/commons.egg-info/SOURCES.txt
src/commons.egg-info/dependency_links.txt
src/commons.egg-info/top_level.txt
src/commons.egg-info/zip-safe
src/frontend/pyhotshot.py
src/test/sqlhash.py
src/test/startup/main.py
src/test/startup/real_main.py
tools/pkg.bash