Metadata-Version: 1.1
Name: commons
Version: 0.7
Summary: Python Commons
Home-page: http://assorted.sourceforge.net/python-commons
Author: Yang Zhang
Author-email: yaaang NOSPAM at REMOVECAPS gmail
License: Python Software Foundation License
Keywords: Python,common,commons,utility,utilities,library,libraries
Platform: any
Classifier: Development Status :: 4 - Beta
Classifier: Environment :: No Input/Output (Daemon)
Classifier: Intended Audience :: Developers
Classifier: License :: OSI Approved :: Python Software Foundation License
Classifier: Operating System :: OS Independent
Classifier: Programming Language :: Python
Classifier: Topic :: Communications
Classifier: Topic :: Database
Classifier: Topic :: Internet
Classifier: Topic :: Software Development :: Libraries :: Python Modules
Classifier: Topic :: System
Classifier: Topic :: System :: Filesystems
Classifier: Topic :: System :: Logging
Classifier: Topic :: System :: Networking
Classifier: Topic :: Text Processing
Classifier: Topic :: Utilities
